[{"spec":{"publisher":{"id":"chosun","name":"조선일보","type":"종합일간지","url":"https://www.chosun.com"},"title":"정치","categories":["politics"],"url":"https://www.chosun.com/arc/outboundfeeds/rss/category/politics/?outputType=xml"},"title":"[속보] 北 방사포·자주포 수십문으로 ‘수도권  타격’ 훈련","partialText":"","date":"2024-03-07T23:54:29.000Z","url":"https://www.chosun.com/politics/diplomacy-defense/2024/03/08/UKP7ZJ2AGVG2RAZQFSEXCSQBHA/"},{"spec":{"publisher":{"id":"chosun","name":"조선일보","type":"종합일간지","url":"https://www.chosun.com"},"title":"정치","categories":["politics"],"url":"https://www.chosun.com/arc/outboundfeeds/rss/category/politics/?outputType=xml"},"title":"이재명 45% 원희룡 41% 인천 계양을 ‘오차범위’[한국갤럽]","partialText":"","date":"2024-03-07T23:13:55.000Z","url":"https://www.chosun.com/politics/election2024/2024/03/08/PX4UPJT64ZCBVP25ZKESPJIPBU/"},{"spec":{"publisher":{"id":"chosun","name":"조선일보","type":"종합일간지","url":"https://www.chosun.com"},"title":"정치","categories":["politics"],"url":"https://www.chosun.com/arc/outboundfeeds/rss/category/politics/?outputType=xml"},"title":"원희룡 “이천수 후원회장 폭행 당해...드릴 든 남성이 협박도”","partialText":"","date":"2024-03-07T23:06:56.000Z","url":"https://www.chosun.com/politics/politics_general/2024/03/08/VEZXJIHNAZB3RLNB6E3IWHZN6Q/"},{"spec":{"publisher":{"id":"chosun","name":"조선일보","type":"종합일간지","url":"https://www.chosun.com"},"title":"정치","categories":["politics"],"url":"https://www.chosun.com/arc/outboundfeeds/rss/category/politics/?outputType=xml"},"title":"박광온 누른 김준혁, 저서엔 “이재명은 정조”","partialText":"","date":"2024-03-07T18:00:00.000Z","url":"https://www.chosun.com/politics/election2024/2024/03/08/2OUXP27PKZH2NE46U5C56NDX4U/"},{"spec":{"publisher":{"id":"chosun","name":"조선일보","type":"종합일간지","url":"https://www.chosun.com"},"title":"정치","categories":["politics"],"url":"https://www.chosun.com/arc/outboundfeeds/rss/category/politics/?outputType=xml"},"title":"北여성 “남편 수입 없는데, 때마다 국가에 선물 바쳐야”","partialText":"북한 노동당 기관지 노동신문은 7일 “나라의 꽃, 사회의 꽃, 가정의 꽃인 우리 여성들에 대한 사랑과 정이 날이 갈 수록 뜨거워지는 가운데 3·8 국제부녀절(세계 여성의 날)을 맞으며 어디서나 축하의 분위기로 설레고 있다”고 전했다. 북한 여성들을 위한 축하공연 등이 준비되고 있다는 보도다.그렇다면 실제 북한 여성들의 삶은 어떨까. 북한전문매체 데일리엔케이(DailyNK)가 정보원을 통해 북한 각지의 20~60대 여성 30명을 조사해 8일 공개한 자료를 본지가 사전 입수해 분석했다.","date":"2024-03-07T18:00:00.000Z","url":"https://www.chosun.com/politics/2024/03/08/534DZL7DTZBCJOGY2DPH42Y2D4/"},{"spec":{"publisher":{"id":"chosun","name":"조선일보","type":"종합일간지","url":"https://www.chosun.com"},"title":"정치","categories":["politics"],"url":"https://www.chosun.com/arc/outboundfeeds/rss/category/politics/?outputType=xml"},"title":"민주·조국당 합치면 여야 지지율 팽팽… 출발선으로 돌아갔다","partialText":"","date":"2024-03-07T18:00:00.000Z","url":"https://www.chosun.com/politics/election2024/2024/03/08/HRZ74LLPKNE4DHTUAXMSIBYYVM/"},{"spec":{"publisher":{"id":"chosun","name":"조선일보","type":"종합일간지","url":"https://www.chosun.com"},"title":"정치","categories":["politics"],"url":"https://www.chosun.com/arc/outboundfeeds/rss/category/politics/?outputType=xml"},"title":"민주당 ‘청년특구’ 서대문갑에 권지웅·김규현·성치훈 3인 경선","partialText":"","date":"2024-03-07T08:54:54.000Z","url":"https://www.chosun.com/politics/election2024/2024/03/07/VB4VJYZXANAVTNW5ZQBD5ZA2ZI/"},{"spec":{"publisher":{"id":"chosun","name":"조선일보","type":"종합일간지","url":"https://www.chosun.com"},"title":"정치","categories":["politics"],"url":"https://www.chosun.com/arc/outboundfeeds/rss/category/politics/?outputType=xml"},"title":"진보당 활동 인사, 시민단체 몫 비례 후보로","partialText":"","date":"2024-03-07T18:00:00.000Z","url":"https://www.chosun.com/politics/election2024/2024/03/08/BKVDVCKDJZAXBJIJWG56CD5NXY/"},{"spec":{"publisher":{"id":"chosun","name":"조선일보","type":"종합일간지","url":"https://www.chosun.com"},"title":"정치","categories":["politics"],"url":"https://www.chosun.com/arc/outboundfeeds/rss/category/politics/?outputType=xml"},"title":"尹 “북한 주민들 자유 확대하는 게 우리의 통일 지향”","partialText":"","date":"2024-03-07T18:00:00.000Z","url":"https://www.chosun.com/politics/blue_house/2024/03/08/USN34AUO7BGO5D6MJVX7OKKKOA/"},{"spec":{"publisher":{"id":"chosun","name":"조선일보","type":"종합일간지","url":"https://www.chosun.com"},"title":"정치","categories":["politics"],"url":"https://www.chosun.com/arc/outboundfeeds/rss/category/politics/?outputType=xml"},"title":"한미가 연합훈련 하자, 돌격소총 든 김정은","partialText":"","date":"2024-03-07T18:00:00.000Z","url":"https://www.chosun.com/politics/diplomacy-defense/2024/03/08/5NALIZL5T5DOPOKQGV7JOU7U7E/"},{"spec":{"publisher":{"id":"chosun","name":"조선일보","type":"종합일간지","url":"https://www.chosun.com"},"title":"정치","categories":["politics"],"url":"https://www.chosun.com/arc/outboundfeeds/rss/category/politics/?outputType=xml"},"title":"수원 후보들과 사진찍는 한동훈","partialText":"","date":"2024-03-07T18:00:00.000Z","url":"https://www.chosun.com/politics/politics_general/2024/03/08/7G4A635N6FHUNBG4OYPB7WQYME/"},{"spec":{"publisher":{"id":"chosun","name":"조선일보","type":"종합일간지","url":"https://www.chosun.com"},"title":"정치","categories":["politics"],"url":"https://www.chosun.com/arc/outboundfeeds/rss/category/politics/?outputType=xml"},"title":"尹대통령 “경인고속도로 지하화 2027년까지 착공”","partialText":"","date":"2024-03-07T18:00:00.000Z","url":"https://www.chosun.com/politics/blue_house/2024/03/08/OTSUNW7CJVC6BIAX3SUTUCBJYM/"},{"spec":{"publisher":{"id":"chosun","name":"조선일보","type":"종합일간지","url":"https://www.chosun.com"},"title":"정치","categories":["politics"],"url":"https://www.chosun.com/arc/outboundfeeds/rss/category/politics/?outputType=xml"},"title":"민주 선대위원장에 임종석·이탄희 거론","partialText":"","date":"2024-03-07T18:00:00.000Z","url":"https://www.chosun.com/politics/election2024/2024/03/08/UMF2IOMRHVCHDIURLN27GP6SAI/"},{"spec":{"publisher":{"id":"chosun","name":"조선일보","type":"종합일간지","url":"https://www.chosun.com"},"title":"정치","categories":["politics"],"url":"https://www.chosun.com/arc/outboundfeeds/rss/category/politics/?outputType=xml"},"title":"비명횡사 다음날, 이재명 “참으로 놀랄 일”… 비명은 “난 비명 아냐”","partialText":"","date":"2024-03-07T18:00:00.000Z","url":"https://www.chosun.com/politics/election2024/2024/03/08/QU5SJQX2XNFGXBPKO2RV7VMNWA/"},{"spec":{"publisher":{"id":"chosun","name":"조선일보","type":"종합일간지","url":"https://www.chosun.com"},"title":"정치","categories":["politics"],"url":"https://www.chosun.com/arc/outboundfeeds/rss/category/politics/?outputType=xml"},"title":"65년 동안 조용한 내조 ‘맹순이’… YS 곁으로","partialText":"","date":"2024-03-07T18:00:00.000Z","url":"https://www.chosun.com/politics/election2024/2024/03/08/SQRFTDLPMBGPXE4BRXH6YE4D5U/"},{"spec":{"publisher":{"id":"chosun","name":"조선일보","type":"종합일간지","url":"https://www.chosun.com"},"title":"정치","categories":["politics"],"url":"https://www.chosun.com/arc/outboundfeeds/rss/category/politics/?outputType=xml"},"title":"간첩 누가 잡나... 與 “다시 국정원” 野 “경찰”","partialText":"","date":"2024-03-07T12:40:47.000Z","url":"https://www.chosun.com/politics/election2024/2024/03/07/P3YJRBVMFZHOXESDE4CZ3JKDNI/"},{"spec":{"publisher":{"id":"chosun","name":"조선일보","type":"종합일간지","url":"https://www.chosun.com"},"title":"정치","categories":["politics"],"url":"https://www.chosun.com/arc/outboundfeeds/rss/category/politics/?outputType=xml"},"title":"65년간 조용한 내조 ‘맹순이’...손명순 여사, YS 곁으로","partialText":"","date":"2024-03-07T09:34:11.000Z","url":"https://www.chosun.com/politics/assembly/2024/03/07/ZU4ANESPHZC35EBGPKH4JWVUEU/"},{"spec":{"publisher":{"id":"chosun","name":"조선일보","type":"종합일간지","url":"https://www.chosun.com"},"title":"정치","categories":["politics"],"url":"https://www.chosun.com/arc/outboundfeeds/rss/category/politics/?outputType=xml"},"title":"단 한발로 北 순항미사일 요격, 공군 KF-16 훈련 공개","partialText":"","date":"2024-03-07T08:41:26.000Z","url":"https://www.chosun.com/politics/diplomacy-defense/2024/03/07/IQ2H4AGH4JCXJKJWKPDTACSMAY/"},{"spec":{"publisher":{"id":"chosun","name":"조선일보","type":"종합일간지","url":"https://www.chosun.com"},"title":"정치","categories":["politics"],"url":"https://www.chosun.com/arc/outboundfeeds/rss/category/politics/?outputType=xml"},"title":"尹대통령 “우리가 지향하는 통일은 北주민 자유 확대하는 것”","partialText":"","date":"2024-03-07T12:30:52.000Z","url":"https://www.chosun.com/politics/blue_house/2024/03/07/SB7WYSNFD5D7TGBI7EIH5DTUHU/"},{"spec":{"publisher":{"id":"chosun","name":"조선일보","type":"종합일간지","url":"https://www.chosun.com"},"title":"정치","categories":["politics"],"url":"https://www.chosun.com/arc/outboundfeeds/rss/category/politics/?outputType=xml"},"title":"비명횡사 질문에 ‘우~’…지지자들 야유에 이재명이 보인 반응은","partialText":"","date":"2024-03-07T11:47:33.000Z","url":"https://www.chosun.com/politics/politics_general/2024/03/07/4KM5BKY6GRHUNEBJC7PNLZH4FM/"},{"spec":{"publisher":{"id":"chosun","name":"조선일보","type":"종합일간지","url":"https://www.chosun.com"},"title":"정치","categories":["politics"],"url":"https://www.chosun.com/arc/outboundfeeds/rss/category/politics/?outputType=xml"},"title":"초급장교 확보난에... 尹대통령, ROTC 임관식 찾아 “지원 아끼지 않겠다”","partialText":"","date":"2024-02-28T07:43:53.000Z","url":"https://www.chosun.com/politics/blue_house/2024/02/28/PYNK4K7AG5A7XDESQCE4GJR3HA/"},{"spec":{"publisher":{"id":"chosun","name":"조선일보","type":"종합일간지","url":"https://www.chosun.com"},"title":"정치","categories":["politics"],"url":"https://www.chosun.com/arc/outboundfeeds/rss/category/politics/?outputType=xml"},"title":"조국 측, ‘울산시장 선거 개입’ 재수사에 “겁먹은 개가 크게 짖는다”","partialText":"","date":"2024-03-07T09:52:12.000Z","url":"https://www.chosun.com/politics/politics_general/2024/03/07/4RFOQ3AEHNANJGTQ6HJG44IOMM/"},{"spec":{"publisher":{"id":"chosun","name":"조선일보","type":"종합일간지","url":"https://www.chosun.com"},"title":"정치","categories":["politics"],"url":"https://www.chosun.com/arc/outboundfeeds/rss/category/politics/?outputType=xml"},"title":"“우린 友黨” 옥중 송영길, 이재명에게 협상제안 자필 편지","partialText":"","date":"2024-03-07T08:46:24.000Z","url":"https://www.chosun.com/politics/politics_general/2024/03/07/7JXUEQXY4VEJLOJKTP5EVAWE7I/"},{"spec":{"publisher":{"id":"chosun","name":"조선일보","type":"종합일간지","url":"https://www.chosun.com"},"title":"정치","categories":["politics"],"url":"https://www.chosun.com/arc/outboundfeeds/rss/category/politics/?outputType=xml"},"title":"“여기 왜 왔어”… 나꼼수 주진우, 한동훈 유세장 갔다가 겪은 일","partialText":"","date":"2024-03-07T08:52:13.000Z","url":"https://www.chosun.com/politics/politics_general/2024/03/07/5SDZZOO4DVALPLZMYSH6EDUQ64/"},{"spec":{"publisher":{"id":"chosun","name":"조선일보","type":"종합일간지","url":"https://www.chosun.com"},"title":"정치","categories":["politics"],"url":"https://www.chosun.com/arc/outboundfeeds/rss/category/politics/?outputType=xml"},"title":"“이재명 양손에 빵, 조국당 찍지 말란 뜻”…  野지지층 ‘몰빵론’ 논쟁","partialText":"","date":"2024-03-07T05:03:18.000Z","url":"https://www.chosun.com/politics/politics_general/2024/03/07/3HWZT3GEWVAPHI2BOTKNERIB5U/"},{"spec":{"publisher":{"id":"chosun","name":"조선일보","type":"종합일간지","url":"https://www.chosun.com"},"title":"정치","categories":["politics"],"url":"https://www.chosun.com/arc/outboundfeeds/rss/category/politics/?outputType=xml"},"title":"초등생들에겐 원희룡보다 이천수… 등굣길에 무슨 일?","partialText":"","date":"2024-03-07T06:32:24.000Z","url":"https://www.chosun.com/politics/politics_general/2024/03/07/TQNCRFDQTNCRBIYIMHIHE3OSRQ/"},{"spec":{"publisher":{"id":"chosun","name":"조선일보","type":"종합일간지","url":"https://www.chosun.com"},"title":"정치","categories":["politics"],"url":"https://www.chosun.com/arc/outboundfeeds/rss/category/politics/?outputType=xml"},"title":"경선 이긴 친명 역사학자 “이재명 생가 앞 200년 소나무 기운 李에게 가”","partialText":"","date":"2024-03-07T07:29:37.000Z","url":"https://www.chosun.com/politics/election2024/2024/03/07/SHASH2B7UFHCTK4MTLFDJIMCZI/"},{"spec":{"publisher":{"id":"chosun","name":"조선일보","type":"종합일간지","url":"https://www.chosun.com"},"title":"정치","categories":["politics"],"url":"https://www.chosun.com/arc/outboundfeeds/rss/category/politics/?outputType=xml"},"title":"신원식 국방 “남침 땐 김정은 정권 종말… 선 응징 후 보고”","partialText":"","date":"2024-03-07T07:41:13.000Z","url":"https://www.chosun.com/politics/diplomacy-defense/2024/03/07/SZV5XHIYRZDGZFJLU3AE7OWSAQ/"},{"spec":{"publisher":{"id":"chosun","name":"조선일보","type":"종합일간지","url":"https://www.chosun.com"},"title":"정치","categories":["politics"],"url":"https://www.chosun.com/arc/outboundfeeds/rss/category/politics/?outputType=xml"},"title":"대통령실 “민생토론회 ‘선거용’ 공세는 잘못된 주장”","partialText":"","date":"2024-03-07T07:16:32.000Z","url":"https://www.chosun.com/politics/politics_general/2024/03/07/QMNA3GXRVZBCXPX6BDOYWZXSQA/"},{"spec":{"publisher":{"id":"chosun","name":"조선일보","type":"종합일간지","url":"https://www.chosun.com"},"title":"정치","categories":["politics"],"url":"https://www.chosun.com/arc/outboundfeeds/rss/category/politics/?outputType=xml"},"title":"전·현직 3명 맞붙는 안산 통합경선도 ‘친명 대 비명’","partialText":"","date":"2024-03-07T06:00:19.000Z","url":"https://www.chosun.com/politics/election2024/2024/03/07/VVONDFEY3JAAFE33TGD46HMCSE/"},{"spec":{"publisher":{"id":"chosun","name":"조선일보","type":"종합일간지","url":"https://www.chosun.com"},"title":"정치","categories":["politics"],"url":"https://www.chosun.com/arc/outboundfeeds/rss/category/politics/?outputType=xml"},"title":"친문·비명 횡사 다음날… 文, 민주 후보와 찍은 사진 올린 까닭은","partialText":"","date":"2024-03-07T05:07:04.000Z","url":"https://www.chosun.com/politics/election2024/2024/03/07/FTIC6WARW5F6BJIG2BL3HWEM4A/"},{"spec":{"publisher":{"id":"chosun","name":"조선일보","type":"종합일간지","url":"https://www.chosun.com"},"title":"정치","categories":["politics"],"url":"https://www.chosun.com/arc/outboundfeeds/rss/category/politics/?outputType=xml"},"title":"국힘 37%, 민주 29%, 조국신당 7%...민주+조국 합치면 여야 팽팽 [NBS]","partialText":"","date":"2024-03-07T02:39:18.000Z","url":"https://www.chosun.com/politics/election2024/2024/03/07/2NEYJRPPYBAAHPWFH7BO4XHPYE/"},{"spec":{"publisher":{"id":"chosun","name":"조선일보","type":"종합일간지","url":"https://www.chosun.com"},"title":"정치","categories":["politics"],"url":"https://www.chosun.com/arc/outboundfeeds/rss/category/politics/?outputType=xml"},"title":"수동에서 전동으로… 호남 ‘자전거 유세’ 與 이정현","partialText":"","date":"2024-03-07T04:47:22.000Z","url":"https://www.chosun.com/politics/election2024/2024/03/07/JZIC3YMSSBEQLP7L5IAAZ3G244/"},{"spec":{"publisher":{"id":"chosun","name":"조선일보","type":"종합일간지","url":"https://www.chosun.com"},"title":"정치","categories":["politics"],"url":"https://www.chosun.com/arc/outboundfeeds/rss/category/politics/?outputType=xml"},"title":"설훈·홍영표, 이낙연 ‘새로운미래’ 입당 “윤석열·이재명 심판”","partialText":"","date":"2024-03-07T02:30:22.000Z","url":"https://www.chosun.com/politics/election2024/2024/03/07/TMSE3OGC7ZD3XAQXWDLY57VIVI/"},{"spec":{"publisher":{"id":"chosun","name":"조선일보","type":"종합일간지","url":"https://www.chosun.com"},"title":"정치","categories":["politics"],"url":"https://www.chosun.com/arc/outboundfeeds/rss/category/politics/?outputType=xml"},"title":"조국, ‘尹찍어내기 감찰’로 해임된 박은정 前검사 영입","partialText":"","date":"2024-03-07T02:01:28.000Z","url":"https://www.chosun.com/politics/election2024/2024/03/07/UULM575TWFBWVLOBWZDLKL6ULQ/"},{"spec":{"publisher":{"id":"chosun","name":"조선일보","type":"종합일간지","url":"https://www.chosun.com"},"title":"정치","categories":["politics"],"url":"https://www.chosun.com/arc/outboundfeeds/rss/category/politics/?outputType=xml"},"title":"옥중 송영길 “2심 유죄 조국은 구속 안되고 정치활동··· 왜 나는”","partialText":"","date":"2024-03-07T00:54:30.000Z","url":"https://www.chosun.com/politics/politics_general/2024/03/07/EWLWK6JPARF73LKFTCGU6J7IYI/"},{"spec":{"publisher":{"id":"chosun","name":"조선일보","type":"종합일간지","url":"https://www.chosun.com"},"title":"정치","categories":["politics"],"url":"https://www.chosun.com/arc/outboundfeeds/rss/category/politics/?outputType=xml"},"title":"개혁신당, 영등포갑에 허은아 공천... 김영주·채현일과 3파전","partialText":"","date":"2024-03-07T01:29:30.000Z","url":"https://www.chosun.com/politics/election2024/2024/03/07/5W6MTK6FVVACXJ4V6QKSDAPM3U/"},{"spec":{"publisher":{"id":"chosun","name":"조선일보","type":"종합일간지","url":"https://www.chosun.com"},"title":"정치","categories":["politics"],"url":"https://www.chosun.com/arc/outboundfeeds/rss/category/politics/?outputType=xml"},"title":"尹대통령 “인천공항 배후에 2026년까지 첨단복합항공단지 조성”","partialText":"","date":"2024-03-07T01:22:10.000Z","url":"https://www.chosun.com/politics/politics_general/2024/03/07/FT64FATY7JCYHP2VDTYNQVMFZY/"},{"spec":{"publisher":{"id":"chosun","name":"조선일보","type":"종합일간지","url":"https://www.chosun.com"},"title":"정치","categories":["politics"],"url":"https://www.chosun.com/arc/outboundfeeds/rss/category/politics/?outputType=xml"},"title":"與 “왜 컷오프인지 자료 공개하라면 언제든 하겠다”","partialText":"","date":"2024-03-07T02:18:14.000Z","url":"https://www.chosun.com/politics/election2024/2024/03/07/GVFKGICCZNGP3PDF6K7QYAQSRA/"},{"spec":{"publisher":{"id":"chosun","name":"조선일보","type":"종합일간지","url":"https://www.chosun.com"},"title":"정치","categories":["politics"],"url":"https://www.chosun.com/arc/outboundfeeds/rss/category/politics/?outputType=xml"},"title":"윤 대통령 지지율 3.5%p↓… 與 지지율도 하락세로 [여론조사공정]","partialText":"","date":"2024-03-06T23:58:05.000Z","url":"https://www.chosun.com/politics/election2024/2024/03/07/OMGJSYNJTBE4PM5ANMX5Y46IBE/"},{"spec":{"publisher":{"id":"chosun","name":"조선일보","type":"종합일간지","url":"https://www.chosun.com"},"title":"정치","categories":["politics"],"url":"https://www.chosun.com/arc/outboundfeeds/rss/category/politics/?outputType=xml"},"title":"한동훈 “총선 승리 후 국정원 대공 수사권 복원할 것”","partialText":"","date":"2024-03-07T01:01:49.000Z","url":"https://www.chosun.com/politics/election2024/2024/03/07/QNDB47XQHZBXNP6E7GLYYXEAZA/"},{"spec":{"publisher":{"id":"chosun","name":"조선일보","type":"종합일간지","url":"https://www.chosun.com"},"title":"정치","categories":["politics"],"url":"https://www.chosun.com/arc/outboundfeeds/rss/category/politics/?outputType=xml"},"title":"[팩트 체크] 권향엽, 김혜경 수행비서 아니다? 배우자 부실장 때 수행 사진 올려","partialText":"","date":"2024-03-06T18:35:44.000Z","url":"https://www.chosun.com/politics/election2024/2024/03/07/CXVBDPH2NZH7NI5M3ZADQYHQFE/"},{"spec":{"publisher":{"id":"chosun","name":"조선일보","type":"종합일간지","url":"https://www.chosun.com"},"title":"정치","categories":["politics"],"url":"https://www.chosun.com/arc/outboundfeeds/rss/category/politics/?outputType=xml"},"title":"[단독] 구조받던 한국 공군, 이젠 美조종사 구한다","partialText":"","date":"2024-03-06T20:00:00.000Z","url":"https://www.chosun.com/politics/diplomacy-defense/2024/03/07/FX4OPG6AYVA3NIUO3K3OGZUTGU/"},{"spec":{"publisher":{"id":"chosun","name":"조선일보","type":"종합일간지","url":"https://www.chosun.com"},"title":"정치","categories":["politics"],"url":"https://www.chosun.com/arc/outboundfeeds/rss/category/politics/?outputType=xml"},"title":"“옛 산업화 주역 구로구 변신, 이름 바꾸기부터 시작하겠다”","partialText":"","date":"2024-03-06T19:20:44.000Z","url":"https://www.chosun.com/politics/election2024/2024/03/07/OMTBKXXFUVCJBGWVJPUCVYXQIQ/"},{"spec":{"publisher":{"id":"chosun","name":"조선일보","type":"종합일간지","url":"https://www.chosun.com"},"title":"정치","categories":["politics"],"url":"https://www.chosun.com/arc/outboundfeeds/rss/category/politics/?outputType=xml"},"title":"가죽재킷 입고 소총 든 김정은 “진짜배기 싸움꾼 보니 마음 든든”","partialText":"","date":"2024-03-06T23:24:57.000Z","url":"https://www.chosun.com/politics/north_korea/2024/03/07/37JQWVYANZB3LFYQF46N7Q4QXM/"},{"spec":{"publisher":{"id":"chosun","name":"조선일보","type":"종합일간지","url":"https://www.chosun.com"},"title":"정치","categories":["politics"],"url":"https://www.chosun.com/arc/outboundfeeds/rss/category/politics/?outputType=xml"},"title":"장제원 “내가 희생 안했다면, 당이 쇄신에 대해 할 얘기 있었겠나”","partialText":"","date":"2024-03-06T19:13:16.000Z","url":"https://www.chosun.com/politics/election2024/2024/03/07/6YGBFXQ6U5HXRIPRQYHIF5KDNQ/"},{"spec":{"publisher":{"id":"chosun","name":"조선일보","type":"종합일간지","url":"https://www.chosun.com"},"title":"정치","categories":["politics"],"url":"https://www.chosun.com/arc/outboundfeeds/rss/category/politics/?outputType=xml"},"title":"“여론조사 20대로 응답해달라” 민주, 정동영에 ‘경고’","partialText":"","date":"2024-03-06T22:21:14.000Z","url":"https://www.chosun.com/politics/politics_general/2024/03/07/RKM5WTBYG5CZ3K5YBLB5BATSFE/"},{"spec":{"publisher":{"id":"chosun","name":"조선일보","type":"종합일간지","url":"https://www.chosun.com"},"title":"정치","categories":["politics"],"url":"https://www.chosun.com/arc/outboundfeeds/rss/category/politics/?outputType=xml"},"title":"사격영웅 진종오·野출신 민영삼, 與 비례대표 신청","partialText":"","date":"2024-03-06T14:29:05.000Z","url":"https://www.chosun.com/politics/election2024/2024/03/06/RRQNKOQX7JFEFD6NR3JHW6O55A/"},{"spec":{"publisher":{"id":"chosun","name":"조선일보","type":"종합일간지","url":"https://www.chosun.com"},"title":"정치","categories":["politics"],"url":"https://www.chosun.com/arc/outboundfeeds/rss/category/politics/?outputType=xml"},"title":"남은 친윤 핵심들, 공천 컷오프 제로","partialText":"","date":"2024-03-06T19:13:41.000Z","url":"https://www.chosun.com/politics/election2024/2024/03/07/7Q2XMD4S6BADFO2DZL43C5INJY/"},{"spec":{"publisher":{"id":"chosun","name":"조선일보","type":"종합일간지","url":"https://www.chosun.com"},"title":"정치","categories":["politics"],"url":"https://www.chosun.com/arc/outboundfeeds/rss/category/politics/?outputType=xml"},"title":"비명 현역에 졌다... 친명 김의겸 경선 탈락","partialText":"","date":"2024-03-06T13:34:31.000Z","url":"https://www.chosun.com/politics/election2024/2024/03/06/66YE4XULYZHQTD5W72VUHZ4NCY/"},{"spec":{"publisher":{"id":"chosun","name":"조선일보","type":"종합일간지","url":"https://www.chosun.com"},"title":"정치","categories":["politics"],"url":"https://www.chosun.com/arc/outboundfeeds/rss/category/politics/?outputType=xml"},"title":"친문·비명 ‘횡사의 밤’...노영민·박광온·윤영찬·김한정 탈락","partialText":"","date":"2024-03-06T14:25:59.000Z","url":"https://www.chosun.com/politics/election2024/2024/03/06/Y6WTYR35ZVGD7LUCNZFVLXQXU4/"},{"spec":{"publisher":{"id":"chosun","name":"조선일보","type":"종합일간지","url":"https://www.chosun.com"},"title":"정치","categories":["politics"],"url":"https://www.chosun.com/arc/outboundfeeds/rss/category/politics/?outputType=xml"},"title":"유경준, ‘컷오프 이의제기’ 철회 “공관위와 진실공방할 의도 없었다”","partialText":"","date":"2024-03-06T14:03:48.000Z","url":"https://www.chosun.com/politics/election2024/2024/03/06/YF3QMXUTFJBUTOPWAK2EJ7AIBE/"},{"spec":{"publisher":{"id":"chosun","name":"조선일보","type":"종합일간지","url":"https://www.chosun.com"},"title":"정치","categories":["politics"],"url":"https://www.chosun.com/arc/outboundfeeds/rss/category/politics/?outputType=xml"},"title":"방사청 “軍전용 육상 위성 발사장 만들겠다…초소형 위성 띄워 北 탐지 강화”","partialText":"","date":"2024-03-06T09:51:48.000Z","url":"https://www.chosun.com/politics/diplomacy-defense/2024/03/06/V6MWV6PPMRDRTGIM5Z42NPGQPI/"},{"spec":{"publisher":{"id":"chosun","name":"조선일보","type":"종합일간지","url":"https://www.chosun.com"},"title":"정치","categories":["politics"],"url":"https://www.chosun.com/arc/outboundfeeds/rss/category/politics/?outputType=xml"},"title":"친문·비명 ‘무더기 횡사’...노영민·박광온·윤영찬·김한정 경선 패배","partialText":"","date":"2024-03-06T13:07:29.000Z","url":"https://www.chosun.com/politics/politics_general/2024/03/06/OK2ALBASH5HGFBQAW36CPHHIT4/"},{"spec":{"publisher":{"id":"chosun","name":"조선일보","type":"종합일간지","url":"https://www.chosun.com"},"title":"정치","categories":["politics"],"url":"https://www.chosun.com/arc/outboundfeeds/rss/category/politics/?outputType=xml"},"title":"권향엽 사천 공방 벌이다가… 민주 “한동훈 고발”, 국힘 “이재명 고발”","partialText":"","date":"2024-03-06T08:21:21.000Z","url":"https://www.chosun.com/politics/politics_general/2024/03/06/FH27R3P73VCN7J5GU2QZUYOJQQ/"},{"spec":{"publisher":{"id":"chosun","name":"조선일보","type":"종합일간지","url":"https://www.chosun.com"},"title":"정치","categories":["politics"],"url":"https://www.chosun.com/arc/outboundfeeds/rss/category/politics/?outputType=xml"},"title":"병무청장 “전공의 사표 수리시 내년부터 순차 입대”","partialText":"","date":"2024-03-06T10:02:50.000Z","url":"https://www.chosun.com/politics/diplomacy-defense/2024/03/06/Q3L6BHFUHZHD3M62FO24ZQF2GA/"},{"spec":{"publisher":{"id":"chosun","name":"조선일보","type":"종합일간지","url":"https://www.chosun.com"},"title":"정치","categories":["politics"],"url":"https://www.chosun.com/arc/outboundfeeds/rss/category/politics/?outputType=xml"},"title":"尹 “국민 건강 위협하는 병원 인적구조 반드시 개혁”","partialText":"","date":"2024-03-06T08:07:52.000Z","url":"https://www.chosun.com/politics/politics_general/2024/03/06/4BT5JHB33FDV3HE47IGZHPG7L4/"},{"spec":{"publisher":{"id":"chosun","name":"조선일보","type":"종합일간지","url":"https://www.chosun.com"},"title":"정치","categories":["politics"],"url":"https://www.chosun.com/arc/outboundfeeds/rss/category/politics/?outputType=xml"},"title":"尹대통령 “의사 불법 집단행동 절대 허용 안돼... 엄중 대응”","partialText":"","date":"2024-03-06T06:04:13.000Z","url":"https://www.chosun.com/politics/politics_general/2024/03/06/4BDPACTEIJBF3O7FKQO2LSSP3U/"},{"spec":{"publisher":{"id":"chosun","name":"조선일보","type":"종합일간지","url":"https://www.chosun.com"},"title":"정치","categories":["politics"],"url":"https://www.chosun.com/arc/outboundfeeds/rss/category/politics/?outputType=xml"},"title":"野 ‘총선용 민생토론회’ 비판에... 尹 “현장서 문제 해결 위한 것”","partialText":"","date":"2024-03-06T06:50:43.000Z","url":"https://www.chosun.com/politics/politics_general/2024/03/06/PKC2UNSVSZD7TDBYUCNNAK7IPI/"},{"spec":{"publisher":{"id":"chosun","name":"조선일보","type":"종합일간지","url":"https://www.chosun.com"},"title":"정치","categories":["politics"],"url":"https://www.chosun.com/arc/outboundfeeds/rss/category/politics/?outputType=xml"},"title":"국보법 수배, 민노총 간부, 민중당 대표도 비례 당선권","partialText":"","date":"2024-03-05T18:00:00.000Z","url":"https://www.chosun.com/politics/election2024/2024/03/06/Q5QFGMDTU5CF7OTSMTMC7RXEWM/"},{"spec":{"publisher":{"id":"chosun","name":"조선일보","type":"종합일간지","url":"https://www.chosun.com"},"title":"정치","categories":["politics"],"url":"https://www.chosun.com/arc/outboundfeeds/rss/category/politics/?outputType=xml"},"title":"‘총선 지지도’ 연합뉴스 조사는 국힘, YTN조사는 민주 앞서","partialText":"","date":"2024-03-06T01:54:50.000Z","url":"https://www.chosun.com/politics/assembly/2024/03/06/WD5FHRGJV5CIBOX2ENTB3DXSPQ/"},{"spec":{"publisher":{"id":"chosun","name":"조선일보","type":"종합일간지","url":"https://www.chosun.com"},"title":"정치","categories":["politics"],"url":"https://www.chosun.com/arc/outboundfeeds/rss/category/politics/?outputType=xml"},"title":"원희룡 “조국 외모 99점...난 거울 보면 스트레스”","partialText":"","date":"2024-03-06T06:11:00.000Z","url":"https://www.chosun.com/politics/politics_general/2024/03/06/QNJWFHZUMJDUPDYTHJWFXPU2BA/"},{"spec":{"publisher":{"id":"chosun","name":"조선일보","type":"종합일간지","url":"https://www.chosun.com"},"title":"정치","categories":["politics"],"url":"https://www.chosun.com/arc/outboundfeeds/rss/category/politics/?outputType=xml"},"title":"안산갑 출마 與 장성민 “안산에 이민청 설치, 국제행정도시 만들 것”","partialText":"","date":"2024-03-06T03:59:06.000Z","url":"https://www.chosun.com/politics/election2024/2024/03/06/MOY7ETSXBVA7LBPQASOQVVCHF4/"},{"spec":{"publisher":{"id":"chosun","name":"조선일보","type":"종합일간지","url":"https://www.chosun.com"},"title":"정치","categories":["politics"],"url":"https://www.chosun.com/arc/outboundfeeds/rss/category/politics/?outputType=xml"},"title":"금태섭, 전태일재단·조선일보 공동기획에 “그만큼 노동시장 이중구조 절박하단 것”","partialText":"","date":"2024-03-06T02:42:18.000Z","url":"https://www.chosun.com/politics/election2024/2024/03/06/KCVKRTXJKRHYLBGTGSOG5SPPBA/"},{"spec":{"publisher":{"id":"chosun","name":"조선일보","type":"종합일간지","url":"https://www.chosun.com"},"title":"정치","categories":["politics"],"url":"https://www.chosun.com/arc/outboundfeeds/rss/category/politics/?outputType=xml"},"title":"국민의힘 37%, 민주당 35%… ‘의대 정원 확대’ 尹 긍정 평가 [갤럽]","partialText":"","date":"2024-02-23T03:01:15.000Z","url":"https://www.chosun.com/politics/election2024/2024/02/23/NBHLBU7PVJFPRJNELUAE7V4Z5Q/"},{"spec":{"publisher":{"id":"chosun","name":"조선일보","type":"종합일간지","url":"https://www.chosun.com"},"title":"정치","categories":["politics"],"url":"https://www.chosun.com/arc/outboundfeeds/rss/category/politics/?outputType=xml"},"title":"“이건 시스템 공천 아니다” 與홍석준·유경준·이채익 등 공개 반발","partialText":"","date":"2024-03-06T02:43:21.000Z","url":"https://www.chosun.com/politics/election2024/2024/03/06/2RRYCWSD2NCALBSUTR3QP62BO4/"},{"spec":{"publisher":{"id":"chosun","name":"조선일보","type":"종합일간지","url":"https://www.chosun.com"},"title":"정치","categories":["politics"],"url":"https://www.chosun.com/arc/outboundfeeds/rss/category/politics/?outputType=xml"},"title":"민주당 ‘공천파동’에 호남 지지율 14%p 하락 [한국갤럽]","partialText":"","date":"2024-03-01T02:09:39.000Z","url":"https://www.chosun.com/politics/election2024/2024/03/01/YYTTB3D2JNANZLEE4T74J6BIRI/"},{"spec":{"publisher":{"id":"chosun","name":"조선일보","type":"종합일간지","url":"https://www.chosun.com"},"title":"정치","categories":["politics"],"url":"https://www.chosun.com/arc/outboundfeeds/rss/category/politics/?outputType=xml"},"title":"유승민 “조국당 지지율 13%, 참담”...유시민 “정치에 도덕·법 대면 안돼”","partialText":"","date":"2024-03-06T02:40:52.000Z","url":"https://www.chosun.com/politics/politics_general/2024/03/06/KZ4PBU2W2BFZXJFG3UFBTBLBXQ/"},{"spec":{"publisher":{"id":"chosun","name":"조선일보","type":"종합일간지","url":"https://www.chosun.com"},"title":"정치","categories":["politics"],"url":"https://www.chosun.com/arc/outboundfeeds/rss/category/politics/?outputType=xml"},"title":"홍영표 “민주가 사라진 ‘가짜 민주당’ 탈당”... 부평을 출마","partialText":"","date":"2024-03-06T02:15:47.000Z","url":"https://www.chosun.com/politics/election2024/2024/03/06/7H6GUEU3FFF3DP4HFLOGN3CIVI/"},{"spec":{"publisher":{"id":"chosun","name":"조선일보","type":"종합일간지","url":"https://www.chosun.com"},"title":"정치","categories":["politics"],"url":"https://www.chosun.com/arc/outboundfeeds/rss/category/politics/?outputType=xml"},"title":"[단독]野영입인재 김구 증손자, 음주운전으로 400만원 벌금형 전력","partialText":"","date":"2024-03-06T01:04:32.000Z","url":"https://www.chosun.com/politics/election2024/2024/03/06/JE3CDFSE5JGMRG5UIKCHREYXPQ/"},{"spec":{"publisher":{"id":"chosun","name":"조선일보","type":"종합일간지","url":"https://www.chosun.com"},"title":"정치","categories":["politics"],"url":"https://www.chosun.com/arc/outboundfeeds/rss/category/politics/?outputType=xml"},"title":"이재명 ‘권성동·김영주 공통점은?’ 공격에...權 ‘李·이석기 공통점은?’","partialText":"","date":"2024-03-06T00:55:01.000Z","url":"https://www.chosun.com/politics/assembly/2024/03/06/LRTZHAMIHVEZFJBDL2AD7QEICI/"},{"spec":{"publisher":{"id":"chosun","name":"조선일보","type":"종합일간지","url":"https://www.chosun.com"},"title":"정치","categories":["politics"],"url":"https://www.chosun.com/arc/outboundfeeds/rss/category/politics/?outputType=xml"},"title":"“강남 주민들이 원하는 정책도 민주당이 수용해 목소리 내야”","partialText":"","date":"2024-03-05T18:00:00.000Z","url":"https://www.chosun.com/politics/election2024/2024/03/06/FP62IMCUBFGMLBUPUSUIUXGNVU/"},{"spec":{"publisher":{"id":"chosun","name":"조선일보","type":"종합일간지","url":"https://www.chosun.com"},"title":"정치","categories":["politics"],"url":"https://www.chosun.com/arc/outboundfeeds/rss/category/politics/?outputType=xml"},"title":"“北 핵기지서 정치범 강제노역… 가면 3년 만에 죽는 곳” 탈북민 증언","partialText":"","date":"2024-03-06T00:37:42.000Z","url":"https://www.chosun.com/politics/north_korea/2024/03/06/EHY6N7JBNRBUJD56GLN3VO7BOU/"},{"spec":{"publisher":{"id":"chosun","name":"조선일보","type":"종합일간지","url":"https://www.chosun.com"},"title":"정치","categories":["politics"],"url":"https://www.chosun.com/arc/outboundfeeds/rss/category/politics/?outputType=xml"},"title":"“김정은, 군부 불만 고조되면 한국 침공 지시…이미 문제 조짐”","partialText":"","date":"2024-03-05T22:12:49.000Z","url":"https://www.chosun.com/politics/north_korea/2024/03/06/FKSIIKSHOBAKXGEDYWRU6K7ALE/"},{"spec":{"publisher":{"id":"chosun","name":"조선일보","type":"종합일간지","url":"https://www.chosun.com"},"title":"정치","categories":["politics"],"url":"https://www.chosun.com/arc/outboundfeeds/rss/category/politics/?outputType=xml"},"title":"‘李 아내 비서’ 사천 논란에… 野, 전략공천 철회하고 경선하기로","partialText":"","date":"2024-03-05T18:00:00.000Z","url":"https://www.chosun.com/politics/election2024/2024/03/06/SSHXE4YCLZG3PGHROLESUIKQBE/"},{"spec":{"publisher":{"id":"chosun","name":"조선일보","type":"종합일간지","url":"https://www.chosun.com"},"title":"정치","categories":["politics"],"url":"https://www.chosun.com/arc/outboundfeeds/rss/category/politics/?outputType=xml"},"title":"박근혜 前대통령 최측근 유영하, 7전 8기 국회 도전","partialText":"","date":"2024-03-05T18:00:00.000Z","url":"https://www.chosun.com/politics/election2024/2024/03/06/PMFCFZXCYNFONJVD6KCVTE77HI/"},{"spec":{"publisher":{"id":"chosun","name":"조선일보","type":"종합일간지","url":"https://www.chosun.com"},"title":"정치","categories":["politics"],"url":"https://www.chosun.com/arc/outboundfeeds/rss/category/politics/?outputType=xml"},"title":"주목받는 친명 유튜버… 김영주도 몰랐던 ‘0점’ 이유, 李보다 먼저 밝혀","partialText":"","date":"2024-03-05T18:00:00.000Z","url":"https://www.chosun.com/politics/election2024/2024/03/06/ACAULC2HJZB6XHSOJ5OVZPGGMA/"},{"spec":{"publisher":{"id":"chosun","name":"조선일보","type":"종합일간지","url":"https://www.chosun.com"},"title":"정치","categories":["politics"],"url":"https://www.chosun.com/arc/outboundfeeds/rss/category/politics/?outputType=xml"},"title":"한동훈, 육아맘들과 간담회","partialText":"","date":"2024-03-05T18:00:00.000Z","url":"https://www.chosun.com/politics/election2024/2024/03/06/2RQCVTCYYJCPDPKHEF2EGULFE4/"},{"spec":{"publisher":{"id":"chosun","name":"조선일보","type":"종합일간지","url":"https://www.chosun.com"},"title":"정치","categories":["politics"],"url":"https://www.chosun.com/arc/outboundfeeds/rss/category/politics/?outputType=xml"},"title":"李, 예정없던 회견 “尹 민생토론회는 불법 선거운동”","partialText":"","date":"2024-03-05T18:00:00.000Z","url":"https://www.chosun.com/politics/election2024/2024/03/06/FGHWG7RRFBGZLNIXTOJRUK3FAA/"},{"spec":{"publisher":{"id":"chosun","name":"조선일보","type":"종합일간지","url":"https://www.chosun.com"},"title":"정치","categories":["politics"],"url":"https://www.chosun.com/arc/outboundfeeds/rss/category/politics/?outputType=xml"},"title":"청년 교통비 30% 환급, 문화비도 15만원 지원","partialText":"","date":"2024-03-05T18:00:00.000Z","url":"https://www.chosun.com/politics/election2024/2024/03/06/PVHZRJMVANBLTCKQNUYBLOT57M/"},{"spec":{"publisher":{"id":"chosun","name":"조선일보","type":"종합일간지","url":"https://www.chosun.com"},"title":"정치","categories":["politics"],"url":"https://www.chosun.com/arc/outboundfeeds/rss/category/politics/?outputType=xml"},"title":"기업 출산 장려금 전액 비과세 혜택","partialText":"","date":"2024-03-05T18:00:00.000Z","url":"https://www.chosun.com/politics/politics_general/2024/03/06/4OE7HFC3UJAIPHYV6OMGDRONNI/"},{"spec":{"publisher":{"id":"chosun","name":"조선일보","type":"종합일간지","url":"https://www.chosun.com"},"title":"정치","categories":["politics"],"url":"https://www.chosun.com/arc/outboundfeeds/rss/category/politics/?outputType=xml"},"title":"이재명과 조국, 사실상 선거 연대","partialText":"","date":"2024-03-05T18:00:00.000Z","url":"https://www.chosun.com/politics/election2024/2024/03/06/26ZKUP2TDJDZREPAMCVAMSXFOE/"},{"spec":{"publisher":{"id":"chosun","name":"조선일보","type":"종합일간지","url":"https://www.chosun.com"},"title":"정치","categories":["politics"],"url":"https://www.chosun.com/arc/outboundfeeds/rss/category/politics/?outputType=xml"},"title":"양산 다녀오면 탈당… 文心인가 우연인가","partialText":"","date":"2024-03-05T18:00:00.000Z","url":"https://www.chosun.com/politics/election2024/2024/03/06/GWJUJNPVQNCNTAAM3EBHBIGNNI/"},{"spec":{"publisher":{"id":"chosun","name":"조선일보","type":"종합일간지","url":"https://www.chosun.com"},"title":"정치","categories":["politics"],"url":"https://www.chosun.com/arc/outboundfeeds/rss/category/politics/?outputType=xml"},"title":"與도 野도 전문가 투입… 불붙은 ‘반도체 벨트’","partialText":"","date":"2024-03-05T18:00:00.000Z","url":"https://www.chosun.com/politics/election2024/2024/03/06/7FGFVGWRYRBADPQPCVRXIVD544/"},{"spec":{"publisher":{"id":"chosun","name":"조선일보","type":"종합일간지","url":"https://www.chosun.com"},"title":"정치","categories":["politics"],"url":"https://www.chosun.com/arc/outboundfeeds/rss/category/politics/?outputType=xml"},"title":"청년도약계좌, 1인가구 기준 연봉 5834만원까지 받아준다","partialText":"","date":"2024-03-05T08:52:48.000Z","url":"https://www.chosun.com/politics/goverment/2024/03/05/EVQERKMX6JG6NLVMJGILTELCNY/"},{"spec":{"publisher":{"id":"chosun","name":"조선일보","type":"종합일간지","url":"https://www.chosun.com"},"title":"정치","categories":["politics"],"url":"https://www.chosun.com/arc/outboundfeeds/rss/category/politics/?outputType=xml"},"title":"조국 “한동훈도 예방…성사되면 따님 입시비리 물을 것”","partialText":"","date":"2024-03-05T13:55:22.000Z","url":"https://www.chosun.com/politics/politics_general/2024/03/05/VYJD2E2IXNAXLHGY4OGL5JAAOM/"},{"spec":{"publisher":{"id":"chosun","name":"조선일보","type":"종합일간지","url":"https://www.chosun.com"},"title":"정치","categories":["politics"],"url":"https://www.chosun.com/arc/outboundfeeds/rss/category/politics/?outputType=xml"},"title":"민주당 ‘사천’ 논란 권향엽 전략공천 철회, 현역 서동용과 경선","partialText":"","date":"2024-03-05T09:11:28.000Z","url":"https://www.chosun.com/politics/election2024/2024/03/05/HIYKH6FUBBA7VOXSET5WUD5XJE/"},{"spec":{"publisher":{"id":"chosun","name":"조선일보","type":"종합일간지","url":"https://www.chosun.com"},"title":"정치","categories":["politics"],"url":"https://www.chosun.com/arc/outboundfeeds/rss/category/politics/?outputType=xml"},"title":"‘한부모 가정’이 못 받은 양육비, 국가가 대신 준다","partialText":"","date":"2024-03-05T05:12:30.000Z","url":"https://www.chosun.com/politics/politics_general/2024/03/05/AMJRRG7VU5D7XOZJZIPDD3PHPI/"},{"spec":{"publisher":{"id":"chosun","name":"조선일보","type":"종합일간지","url":"https://www.chosun.com"},"title":"정치","categories":["politics"],"url":"https://www.chosun.com/arc/outboundfeeds/rss/category/politics/?outputType=xml"},"title":"한미 정부 방위비 분담금 협상 대표 임명, ‘5배 증액’ 트럼프 리스크 대비","partialText":"한미 양국이 2026년부터 적용될 제12차 방위비분담특별협정(SMA)를 협상할 수석대표를 5일 각각 임명했다. 이로써 내년 말 종료되는 방위비 협정의 조기 협상 개시가 공식화됐다. 협정 종료까지 약 2년이 남은 상황에서 협상 대표를 임명하고 본격적 협상에 돌입하는 것은 이례적인 일이다. 첫 집권 당시 한국 방위비 분담금의 5배 증액을 요구했던 도널드 트럼프 전 대통령이 오는 11월 미국 대선에 승리할 가능성에 대비한 조치로 풀이된다.","date":"2024-03-05T08:52:06.000Z","url":"https://www.chosun.com/politics/politics_general/2024/03/05/A5CWFEIMVFEWFHRXVNTW4YUILA/"},{"spec":{"publisher":{"id":"chosun","name":"조선일보","type":"종합일간지","url":"https://www.chosun.com"},"title":"정치","categories":["politics"],"url":"https://www.chosun.com/arc/outboundfeeds/rss/category/politics/?outputType=xml"},"title":"이재명에 토론 제안 한동훈 “정청래 데려와도, 묵비권 행사해도 OK”","partialText":"","date":"2024-03-05T07:49:38.000Z","url":"https://www.chosun.com/politics/politics_general/2024/03/05/3XOHYZDTJJGWLOZVV4FX5BE6G4/"},{"spec":{"publisher":{"id":"chosun","name":"조선일보","type":"종합일간지","url":"https://www.chosun.com"},"title":"정치","categories":["politics"],"url":"https://www.chosun.com/arc/outboundfeeds/rss/category/politics/?outputType=xml"},"title":"이재명 “김영주, 이상한 핑계 대고 나가... 영등포갑 승부 끝났다”","partialText":"","date":"2024-03-05T06:59:43.000Z","url":"https://www.chosun.com/politics/election2024/2024/03/05/G2WNR4FM4RCJRP2IS45DC32FKM/"},{"spec":{"publisher":{"id":"chosun","name":"조선일보","type":"종합일간지","url":"https://www.chosun.com"},"title":"정치","categories":["politics"],"url":"https://www.chosun.com/arc/outboundfeeds/rss/category/politics/?outputType=xml"},"title":"與김용태, 고양정 출마선언... “일산서구 집값 화끈하게 올리겠다”","partialText":"","date":"2024-03-05T06:32:57.000Z","url":"https://www.chosun.com/politics/election2024/2024/03/05/AADXIKEWAVDAVCVKVAEBS4LUOE/"},{"spec":{"publisher":{"id":"chosun","name":"조선일보","type":"종합일간지","url":"https://www.chosun.com"},"title":"정치","categories":["politics"],"url":"https://www.chosun.com/arc/outboundfeeds/rss/category/politics/?outputType=xml"},"title":"與 대구 달서갑 유영하·서울 강남병 고동진 공천","partialText":"","date":"2024-03-05T05:52:17.000Z","url":"https://www.chosun.com/politics/election2024/2024/03/05/T2HZ5WRD6RBJ7FNDTQSZTIWBX4/"},{"spec":{"publisher":{"id":"chosun","name":"조선일보","type":"종합일간지","url":"https://www.chosun.com"},"title":"정치","categories":["politics"],"url":"https://www.chosun.com/arc/outboundfeeds/rss/category/politics/?outputType=xml"},"title":"손 맞잡은 이재명·조국 “윤석열 정권 종식 위해 협력·단결”","partialText":"","date":"2024-03-05T02:45:32.000Z","url":"https://www.chosun.com/politics/election2024/2024/03/05/SMNC7D3PMFAMTDFBQBUCXISW3E/"},{"spec":{"publisher":{"id":"chosun","name":"조선일보","type":"종합일간지","url":"https://www.chosun.com"},"title":"정치","categories":["politics"],"url":"https://www.chosun.com/arc/outboundfeeds/rss/category/politics/?outputType=xml"},"title":"野위성정당 비례후보에 또 용혜인, 3주전 민주 탈당 文비서관도","partialText":"","date":"2024-03-05T00:59:43.000Z","url":"https://www.chosun.com/politics/election2024/2024/03/05/QCLYR4B4IFD7DBI7HWIUNIYDQE/"},{"spec":{"publisher":{"id":"chosun","name":"조선일보","type":"종합일간지","url":"https://www.chosun.com"},"title":"정치","categories":["politics"],"url":"https://www.chosun.com/arc/outboundfeeds/rss/category/politics/?outputType=xml"},"title":"與 서초을 신동욱 공천... 김영주·박민식 전략공천","partialText":"","date":"2024-03-05T00:43:29.000Z","url":"https://www.chosun.com/politics/election2024/2024/03/05/VIH7FAUWRFDURNB4HKLSBU5GV4/"},{"spec":{"publisher":{"id":"chosun","name":"조선일보","type":"종합일간지","url":"https://www.chosun.com"},"title":"정치","categories":["politics"],"url":"https://www.chosun.com/arc/outboundfeeds/rss/category/politics/?outputType=xml"},"title":"호남 28개 全지역구에 국민의힘 후보","partialText":"","date":"2024-03-03T18:00:00.000Z","url":"https://www.chosun.com/politics/election2024/2024/03/04/JOV62AHYXFCFPHSES5KCD3GZ6E/"},{"spec":{"publisher":{"id":"chosun","name":"조선일보","type":"종합일간지","url":"https://www.chosun.com"},"title":"정치","categories":["politics"],"url":"https://www.chosun.com/arc/outboundfeeds/rss/category/politics/?outputType=xml"},"title":"맞으면 바로 쏜다… 한동훈 ‘틱톡 화법’, 與 최전선 무기로","partialText":"","date":"2024-03-04T18:46:02.000Z","url":"https://www.chosun.com/politics/2024/03/05/HM6SATMITZFDTABGJLC7WJ2KAQ/"},{"spec":{"publisher":{"id":"chosun","name":"조선일보","type":"종합일간지","url":"https://www.chosun.com"},"title":"정치","categories":["politics"],"url":"https://www.chosun.com/arc/outboundfeeds/rss/category/politics/?outputType=xml"},"title":"이종섭 호주·김판규 나이지리아 대사","partialText":"","date":"2024-03-04T19:45:15.000Z","url":"https://www.chosun.com/politics/politics_general/2024/03/05/3KOX73NVRBACZDF5UYLJ324YN4/"},{"spec":{"publisher":{"id":"chosun","name":"조선일보","type":"종합일간지","url":"https://www.chosun.com"},"title":"정치","categories":["politics"],"url":"https://www.chosun.com/arc/outboundfeeds/rss/category/politics/?outputType=xml"},"title":"유시춘 EBS 이사장, 법카로 수천만원 사적 사용","partialText":"","date":"2024-03-04T19:14:37.000Z","url":"https://www.chosun.com/politics/goverment/2024/03/05/I5F2MRYPRVC43IAVPHB2HXRHLI/"}]